m2c2kit_data_cli/__init__.py
m2c2kit_data_cli/__main__.py
m2c2kit_data_cli/api.py
m2c2kit_data_cli/constants.py
m2c2kit_data_cli/jupyterguts.py
m2c2kit_data_cli/main.py
m2c2kit_data_cli-0.1.14.dist-info/LICENSE
m2c2kit_data_cli-0.1.14.dist-info/METADATA
m2c2kit_data_cli-0.1.14.dist-info/WHEEL
m2c2kit_data_cli-0.1.14.dist-info/entry_points.txt
m2c2kit_data_cli-0.1.14.dist-info/RECORD
